{
  "session_id": "f0673498-cfa6-4472-898e-51395156a22a",
  "is_bot": true,
  "bot_type": "fixed_coord",
  "bot_description": "좌표 고정 봇",
  "mode": "A",
  "page_entry_time": "2026-01-29T18:33:42.940828",
  "page_exit_time": "2026-01-29T18:33:50.940828",
  "total_duration_ms": 8604,
  "user_ip": "192.168.204.216",
  "user_id": "bot_fixed_coord_8752",
  "mouse_trajectory": [],
  "clicks": [
    {
      "x": 418,
      "y": 286,
      "target": "seat_31",
      "timestamp": 0
    },
    {
      "x": 366,
      "y": 353,
      "target": "seat_350",
      "timestamp": 253
    },
    {
      "x": 520,
      "y": 222,
      "target": "seat_163",
      "timestamp": 506
    },
    {
      "x": 405,
      "y": 262,
      "target": "seat_55",
      "timestamp": 759
    },
    {
      "x": 571,
      "y": 296,
      "target": "seat_213",
      "timestamp": 1012
    },
    {
      "x": 355,
      "y": 390,
      "target": "seat_57",
      "timestamp": 1265
    },
    {
      "x": 330,
      "y": 369,
      "target": "seat_42",
      "timestamp": 1519
    },
    {
      "x": 513,
      "y": 247,
      "target": "seat_405",
      "timestamp": 1772
    },
    {
      "x": 592,
      "y": 205,
      "target": "seat_559",
      "timestamp": 2025
    },
    {
      "x": 427,
      "y": 303,
      "target": "seat_453",
      "timestamp": 2278
    },
    {
      "x": 342,
      "y": 307,
      "target": "seat_176",
      "timestamp": 2531
    },
    {
      "x": 490,
      "y": 380,
      "target": "seat_291",
      "timestamp": 2785
    },
    {
      "x": 553,
      "y": 300,
      "target": "seat_20",
      "timestamp": 3038
    },
    {
      "x": 490,
      "y": 298,
      "target": "seat_352",
      "timestamp": 3291
    }
  ],
  "hovers": [],
  "captcha_attempts": 2,
  "captcha_time_ms": 496,
  "bot_score": 0.8208187648374291
}