{
  "session_id": "book_j66hmuuo",
  "stage": "book",
  "user_ip": "127.0.0.1",
  "user_id": "511ce0b4-cf18-43cf-923f-c7381e8240a2",
  "user_email": "magellankr@outlook.kr",
  "created_at": "2026-01-29T20:47:24.723424",
  "performance_id": "perf002",
  "selected_date": "2026-02-01",
  "selected_time": "14:00",
  "booking_start_time": "2026-01-29T11:46:56.572Z",
  "captcha": {
    "start_time": "2026-01-29T11:46:56.572Z",
    "end_time": "2026-01-29T11:47:09.699Z",
    "attempts": [
      {
        "action": "attempt",
        "input": "TXDRLN",
        "correct": true,
        "time_ms": 13127,
        "attempt_number": 1,
        "timestamp": "2026-01-29T11:47:09.699Z"
      }
    ],
    "success": true,
    "mouse_trajectory": [
      {
        "x": 720,
        "y": 591,
        "t": 10424
      },
      {
        "x": 723,
        "y": 597,
        "t": 10481
      },
      {
        "x": 727,
        "y": 607,
        "t": 10536
      },
      {
        "x": 731,
        "y": 616,
        "t": 10591
      },
      {
        "x": 734,
        "y": 622,
        "t": 10647
      }
    ]
  },
  "seats": {
    "selected": [],
    "taken_by_others": [],
    "selection_time": null
  },
  "discount": {
    "type": "normal",
    "selection_time": "2026-01-29T11:47:20.313Z"
  },
  "delivery": {
    "method": "pickup",
    "fee": 0,
    "selection_time": "2026-01-29T11:47:22.477Z"
  },
  "payment": {
    "method": "bank",
    "selection_time": "2026-01-29T11:47:24.721Z"
  },
  "booking_end_time": "2026-01-29T11:47:24.721Z",
  "section_selection": {
    "start_time": "2026-01-29T11:47:09.741Z",
    "clicks": [
      {
        "section": "VIP-L",
        "timestamp": "2026-01-29T11:47:11.335Z"
      }
    ],
    "final_section": "VIP-L",
    "end_time": "2026-01-29T11:47:12.138Z",
    "final_grade": "VIP",
    "mouse_trajectory": []
  },
  "seat_selection": {
    "seats": [
      "VIP-A5"
    ],
    "section": "VIP-L",
    "grade": "VIP",
    "start_time": "2026-01-29T11:47:12.175Z",
    "end_time": "2026-01-29T11:47:18.159Z",
    "duration_ms": 5984,
    "clicks": [
      {
        "x": 448.5,
        "y": 394,
        "target": "VIP-A5",
        "timestamp": 1740
      }
    ],
    "hovers": []
  },
  "mouse_trajectory_seats": [],
  "mouse_trajectory_discount": [],
  "booker": {
    "phone": "1111111111",
    "email": "magellankr@outlook.kr",
    "input_time": "2026-01-29T11:47:22.477Z"
  },
  "mouse_trajectory_booker": [],
  "mouse_trajectory_payment": []
}