{
  "session_id": "book_s8tzz7zp",
  "stage": "book",
  "user_ip": "127.0.0.1",
  "user_id": "511ce0b4-cf18-43cf-923f-c7381e8240a2",
  "user_email": "magellankr@outlook.kr",
  "created_at": "2026-01-29T20:12:35.503669",
  "performance_id": "perf002",
  "selected_date": "2026-02-01",
  "selected_time": "14:00",
  "booking_start_time": "2026-01-29T11:10:29.747Z",
  "captcha": {
    "start_time": "2026-01-29T11:11:54.626Z",
    "end_time": "2026-01-29T11:12:20.493Z",
    "attempts": [
      {
        "action": "refresh",
        "timestamp": "2026-01-29T11:10:59.468Z"
      },
      {
        "action": "refresh",
        "timestamp": "2026-01-29T11:11:50.710Z"
      },
      {
        "action": "refresh",
        "timestamp": "2026-01-29T11:11:54.626Z"
      },
      {
        "action": "attempt",
        "input": "LZXEEN",
        "correct": true,
        "time_ms": 25867,
        "attempt_number": 1,
        "timestamp": "2026-01-29T11:12:20.493Z"
      }
    ],
    "success": true,
    "mouse_trajectory": [
      {
        "x": 725,
        "y": 589,
        "t": 10269
      },
      {
        "x": 726,
        "y": 588,
        "t": 10324
      },
      {
        "x": 733,
        "y": 586,
        "t": 10428
      },
      {
        "x": 744,
        "y": 582,
        "t": 10533
      },
      {
        "x": 751,
        "y": 580,
        "t": 10630
      },
      {
        "x": 752,
        "y": 579,
        "t": 10685
      },
      {
        "x": 762,
        "y": 572,
        "t": 29268
      },
      {
        "x": 789,
        "y": 553,
        "t": 29324
      },
      {
        "x": 880,
        "y": 486,
        "t": 29421
      },
      {
        "x": 907,
        "y": 467,
        "t": 29477
      },
      {
        "x": 916,
        "y": 460,
        "t": 29531
      },
      {
        "x": 911,
        "y": 464,
        "t": 37428
      },
      {
        "x": 896,
        "y": 475,
        "t": 37483
      },
      {
        "x": 834,
        "y": 519,
        "t": 37586
      },
      {
        "x": 799,
        "y": 546,
        "t": 37642
      },
      {
        "x": 758,
        "y": 575,
        "t": 37739
      },
      {
        "x": 753,
        "y": 579,
        "t": 37789
      },
      {
        "x": 757,
        "y": 576,
        "t": 56587
      },
      {
        "x": 769,
        "y": 567,
        "t": 56643
      },
      {
        "x": 1485,
        "y": 296,
        "t": 56693
      },
      {
        "x": 1311,
        "y": 354,
        "t": 56743
      },
      {
        "x": 1133,
        "y": 399,
        "t": 56794
      },
      {
        "x": 880,
        "y": 486,
        "t": 56857
      },
      {
        "x": 989,
        "y": 428,
        "t": 56912
      },
      {
        "x": 912,
        "y": 462,
        "t": 56975
      },
      {
        "x": 757,
        "y": 615,
        "t": 57031
      },
      {
        "x": 710,
        "y": 662,
        "t": 57086
      },
      {
        "x": 705,
        "y": 670,
        "t": 57195
      },
      {
        "x": 732,
        "y": 659,
        "t": 57246
      },
      {
        "x": 763,
        "y": 634,
        "t": 57310
      },
      {
        "x": 765,
        "y": 627,
        "t": 57364
      },
      {
        "x": 765,
        "y": 626,
        "t": 57426
      },
      {
        "x": 764,
        "y": 626,
        "t": 57627
      },
      {
        "x": 761,
        "y": 625,
        "t": 57810
      },
      {
        "x": 760,
        "y": 623,
        "t": 58077
      },
      {
        "x": 764,
        "y": 617,
        "t": 58142
      },
      {
        "x": 821,
        "y": 576,
        "t": 58197
      },
      {
        "x": 1166,
        "y": 369,
        "t": 58259
      },
      {
        "x": 1380,
        "y": 234,
        "t": 58315
      },
      {
        "x": 1483,
        "y": 160,
        "t": 58378
      },
      {
        "x": 1473,
        "y": 166,
        "t": 64900
      },
      {
        "x": 1442,
        "y": 183,
        "t": 64954
      },
      {
        "x": 1392,
        "y": 212,
        "t": 65004
      },
      {
        "x": 1321,
        "y": 253,
        "t": 65059
      },
      {
        "x": 1230,
        "y": 305,
        "t": 65115
      },
      {
        "x": 1006,
        "y": 434,
        "t": 65219
      },
      {
        "x": 915,
        "y": 486,
        "t": 65274
      },
      {
        "x": 794,
        "y": 556,
        "t": 65378
      },
      {
        "x": 763,
        "y": 573,
        "t": 65440
      },
      {
        "x": 1488,
        "y": 160,
        "t": 69226
      },
      {
        "x": 1383,
        "y": 69,
        "t": 74635
      },
      {
        "x": 1000,
        "y": 379,
        "t": 74739
      },
      {
        "x": 863,
        "y": 490,
        "t": 74795
      },
      {
        "x": 780,
        "y": 557,
        "t": 74850
      },
      {
        "x": 1488,
        "y": 610,
        "t": 78961
      },
      {
        "x": 1441,
        "y": 642,
        "t": 79030
      },
      {
        "x": 1322,
        "y": 651,
        "t": 79099
      },
      {
        "x": 1085,
        "y": 675,
        "t": 79160
      },
      {
        "x": 1007,
        "y": 680,
        "t": 79210
      },
      {
        "x": 990,
        "y": 680,
        "t": 79266
      },
      {
        "x": 989,
        "y": 680,
        "t": 79344
      },
      {
        "x": 971,
        "y": 682,
        "t": 79394
      },
      {
        "x": 936,
        "y": 688,
        "t": 79445
      },
      {
        "x": 915,
        "y": 692,
        "t": 79495
      },
      {
        "x": 881,
        "y": 697,
        "t": 79565
      },
      {
        "x": 862,
        "y": 701,
        "t": 79641
      },
      {
        "x": 852,
        "y": 703,
        "t": 79697
      },
      {
        "x": 849,
        "y": 700,
        "t": 79780
      },
      {
        "x": 833,
        "y": 668,
        "t": 79849
      },
      {
        "x": 826,
        "y": 641,
        "t": 79912
      },
      {
        "x": 841,
        "y": 594,
        "t": 79981
      },
      {
        "x": 876,
        "y": 534,
        "t": 80044
      },
      {
        "x": 881,
        "y": 520,
        "t": 80099
      },
      {
        "x": 890,
        "y": 501,
        "t": 80162
      },
      {
        "x": 892,
        "y": 491,
        "t": 80231
      },
      {
        "x": 892,
        "y": 489,
        "t": 80294
      },
      {
        "x": 894,
        "y": 486,
        "t": 80344
      },
      {
        "x": 897,
        "y": 482,
        "t": 80411
      },
      {
        "x": 902,
        "y": 475,
        "t": 80461
      },
      {
        "x": 905,
        "y": 472,
        "t": 80516
      },
      {
        "x": 905,
        "y": 471,
        "t": 81080
      },
      {
        "x": 898,
        "y": 472,
        "t": 81148
      },
      {
        "x": 852,
        "y": 502,
        "t": 81211
      },
      {
        "x": 805,
        "y": 560,
        "t": 81266
      },
      {
        "x": 785,
        "y": 595,
        "t": 81329
      },
      {
        "x": 779,
        "y": 601,
        "t": 81577
      },
      {
        "x": 759,
        "y": 621,
        "t": 81643
      },
      {
        "x": 739,
        "y": 641,
        "t": 81697
      },
      {
        "x": 738,
        "y": 641,
        "t": 81959
      },
      {
        "x": 741,
        "y": 638,
        "t": 84177
      },
      {
        "x": 750,
        "y": 629,
        "t": 84232
      },
      {
        "x": 764,
        "y": 614,
        "t": 84288
      },
      {
        "x": 785,
        "y": 593,
        "t": 84343
      },
      {
        "x": 842,
        "y": 535,
        "t": 84448
      },
      {
        "x": 869,
        "y": 508,
        "t": 84503
      },
      {
        "x": 890,
        "y": 487,
        "t": 84559
      },
      {
        "x": 904,
        "y": 472,
        "t": 84614
      },
      {
        "x": 913,
        "y": 463,
        "t": 84676
      },
      {
        "x": 907,
        "y": 467,
        "t": 92468
      },
      {
        "x": 834,
        "y": 519,
        "t": 92578
      },
      {
        "x": 762,
        "y": 572,
        "t": 92683
      },
      {
        "x": 738,
        "y": 640,
        "t": 100177
      },
      {
        "x": 731,
        "y": 632,
        "t": 100238
      },
      {
        "x": 724,
        "y": 624,
        "t": 100447
      },
      {
        "x": 767,
        "y": 627,
        "t": 100516
      },
      {
        "x": 812,
        "y": 615,
        "t": 100566
      },
      {
        "x": 930,
        "y": 519,
        "t": 100626
      },
      {
        "x": 1078,
        "y": 447,
        "t": 100677
      },
      {
        "x": 1131,
        "y": 418,
        "t": 100727
      },
      {
        "x": 1233,
        "y": 387,
        "t": 100793
      },
      {
        "x": 1348,
        "y": 380,
        "t": 100843
      },
      {
        "x": 1369,
        "y": 380,
        "t": 100893
      },
      {
        "x": 1326,
        "y": 513,
        "t": 101982
      },
      {
        "x": 1075,
        "y": 542,
        "t": 102037
      },
      {
        "x": 896,
        "y": 563,
        "t": 102100
      },
      {
        "x": 789,
        "y": 575,
        "t": 102155
      },
      {
        "x": 753,
        "y": 579,
        "t": 102211
      },
      {
        "x": 1416,
        "y": 743,
        "t": 105311
      },
      {
        "x": 1274,
        "y": 781,
        "t": 105377
      },
      {
        "x": 1189,
        "y": 776,
        "t": 105427
      },
      {
        "x": 1171,
        "y": 766,
        "t": 105477
      },
      {
        "x": 1135,
        "y": 743,
        "t": 105527
      },
      {
        "x": 1101,
        "y": 735,
        "t": 105596
      },
      {
        "x": 978,
        "y": 720,
        "t": 105661
      },
      {
        "x": 914,
        "y": 710,
        "t": 105717
      },
      {
        "x": 898,
        "y": 705,
        "t": 105779
      },
      {
        "x": 886,
        "y": 685,
        "t": 105849
      },
      {
        "x": 860,
        "y": 644,
        "t": 105911
      },
      {
        "x": 853,
        "y": 641,
        "t": 105967
      },
      {
        "x": 848,
        "y": 640,
        "t": 106029
      },
      {
        "x": 845,
        "y": 639,
        "t": 106161
      },
      {
        "x": 843,
        "y": 634,
        "t": 106227
      },
      {
        "x": 840,
        "y": 632,
        "t": 106526
      }
    ]
  },
  "seats": {
    "selected": [],
    "taken_by_others": [],
    "selection_time": null
  },
  "discount": {
    "type": "normal",
    "selection_time": "2026-01-29T11:12:31.129Z"
  },
  "delivery": {
    "method": "pickup",
    "fee": 0,
    "selection_time": "2026-01-29T11:12:33.214Z"
  },
  "payment": {
    "method": "bank",
    "selection_time": "2026-01-29T11:12:35.501Z"
  },
  "booking_end_time": "2026-01-29T11:12:35.501Z",
  "section_selection": {
    "start_time": "2026-01-29T11:12:20.835Z",
    "clicks": [
      {
        "section": "VIP-R",
        "timestamp": "2026-01-29T11:12:21.431Z"
      },
      {
        "section": "VIP-L",
        "timestamp": "2026-01-29T11:12:22.361Z"
      }
    ],
    "final_section": "VIP-L",
    "end_time": "2026-01-29T11:12:23.067Z",
    "final_grade": "VIP",
    "mouse_trajectory": [
      {
        "x": 840,
        "y": 626,
        "t": 61
      },
      {
        "x": 860,
        "y": 583,
        "t": 178
      },
      {
        "x": 894,
        "y": 508,
        "t": 282
      },
      {
        "x": 914,
        "y": 465,
        "t": 393
      }
    ]
  },
  "seat_selection": {
    "seats": [
      "VIP-A5"
    ],
    "section": "VIP-L",
    "grade": "VIP",
    "start_time": "2026-01-29T11:12:23.108Z",
    "end_time": "2026-01-29T11:12:28.908Z",
    "duration_ms": 5800,
    "clicks": [
      {
        "x": 448.5,
        "y": 394,
        "target": "VIP-A5",
        "timestamp": 1672
      }
    ],
    "hovers": []
  },
  "mouse_trajectory_seats": [
    {
      "x": 919,
      "y": 459,
      "timestamp": 5641
    },
    {
      "x": 941,
      "y": 449,
      "timestamp": 5739
    },
    {
      "x": 960,
      "y": 440,
      "timestamp": 5794
    }
  ],
  "mouse_trajectory_discount": [
    {
      "x": 1016,
      "y": 415,
      "t": 46
    },
    {
      "x": 1051,
      "y": 400,
      "t": 102
    },
    {
      "x": 1107,
      "y": 375,
      "t": 199
    },
    {
      "x": 1126,
      "y": 366,
      "t": 254
    },
    {
      "x": 1148,
      "y": 356,
      "t": 359
    }
  ],
  "booker": {
    "phone": "1111111111",
    "email": "magellankr@outlook.kr",
    "input_time": "2026-01-29T11:12:33.214Z"
  },
  "mouse_trajectory_booker": [],
  "mouse_trajectory_payment": []
}