{
  "session_id": "perf_pbguzbg3",
  "stage": "perf",
  "user_ip": "127.0.0.1",
  "user_id": "511ce0b4-cf18-43cf-923f-c7381e8240a2",
  "user_email": "magellankr@outlook.kr",
  "created_at": "2026-01-23T17:03:04.249872",
  "page_entry_time": "2026-01-23T08:02:44.189Z",
  "performance_id": "perf008",
  "actions": [
    {
      "action": "card_click",
      "target": "perf008",
      "timestamp": "2026-01-23T08:02:52.357Z"
    },
    {
      "action": "time_select",
      "target": "18:00",
      "timestamp": "2026-01-23T08:02:54.004Z"
    },
    {
      "action": "date_select",
      "target": "2026-07-06",
      "timestamp": "2026-01-23T08:02:54.508Z"
    },
    {
      "action": "booking_start",
      "target": "perf008",
      "date": "2026-07-06",
      "time": "18:00",
      "timestamp": "2026-01-23T08:03:03.940Z"
    }
  ],
  "mouse_trajectory": [
    {
      "x": 1682,
      "y": 296,
      "timestamp": 6975
    },
    {
      "x": 1294,
      "y": 602,
      "timestamp": 7080
    },
    {
      "x": 1274,
      "y": 684,
      "timestamp": 7348
    },
    {
      "x": 1264,
      "y": 666,
      "timestamp": 7452
    },
    {
      "x": 1256,
      "y": 664,
      "timestamp": 7563
    },
    {
      "x": 1238,
      "y": 665,
      "timestamp": 7673
    },
    {
      "x": 1046,
      "y": 776,
      "timestamp": 7778
    },
    {
      "x": 874,
      "y": 857,
      "timestamp": 7882
    },
    {
      "x": 842,
      "y": 860,
      "timestamp": 8014
    },
    {
      "x": 848,
      "y": 845,
      "timestamp": 8421
    },
    {
      "x": 910,
      "y": 720,
      "timestamp": 8527
    },
    {
      "x": 917,
      "y": 616,
      "timestamp": 8679
    },
    {
      "x": 900,
      "y": 601,
      "timestamp": 8782
    },
    {
      "x": 882,
      "y": 578,
      "timestamp": 8887
    },
    {
      "x": 825,
      "y": 505,
      "timestamp": 8997
    },
    {
      "x": 816,
      "y": 494,
      "timestamp": 9175
    },
    {
      "x": 777,
      "y": 532,
      "timestamp": 9282
    },
    {
      "x": 745,
      "y": 576,
      "timestamp": 9386
    },
    {
      "x": 722,
      "y": 592,
      "timestamp": 9490
    },
    {
      "x": 650,
      "y": 613,
      "timestamp": 9594
    },
    {
      "x": 645,
      "y": 613,
      "timestamp": 9823
    },
    {
      "x": 734,
      "y": 564,
      "timestamp": 9928
    },
    {
      "x": 765,
      "y": 558,
      "timestamp": 10032
    },
    {
      "x": 818,
      "y": 538,
      "timestamp": 10136
    },
    {
      "x": 825,
      "y": 536,
      "timestamp": 10365
    },
    {
      "x": 848,
      "y": 521,
      "timestamp": 10587
    },
    {
      "x": 909,
      "y": 508,
      "timestamp": 10727
    },
    {
      "x": 953,
      "y": 536,
      "timestamp": 10831
    },
    {
      "x": 1025,
      "y": 614,
      "timestamp": 10942
    },
    {
      "x": 1024,
      "y": 733,
      "timestamp": 11046
    },
    {
      "x": 1022,
      "y": 736,
      "timestamp": 11168
    },
    {
      "x": 1041,
      "y": 728,
      "timestamp": 11275
    },
    {
      "x": 1077,
      "y": 706,
      "timestamp": 11379
    },
    {
      "x": 1080,
      "y": 700,
      "timestamp": 19287
    },
    {
      "x": 1037,
      "y": 694,
      "timestamp": 19391
    },
    {
      "x": 1020,
      "y": 689,
      "timestamp": 19503
    }
  ],
  "card_clicks": [
    {
      "performance_id": "perf008",
      "performance_title": "2026 NCT 127 월드투어",
      "timestamp": "2026-01-23T08:02:52.357Z"
    }
  ],
  "date_selections": [
    {
      "date": "2026-07-06",
      "timestamp": "2026-01-23T08:02:54.508Z"
    }
  ],
  "time_selections": [
    {
      "time": "18:00",
      "timestamp": "2026-01-23T08:02:54.004Z"
    }
  ],
  "page_exit_time": "2026-01-23T08:03:03.940Z",
  "selected_date": "2026-07-06",
  "selected_time": "18:00"
}